h_yt_downloader/__init__.py
h_yt_downloader/main.py
h_yt_downloader-0.2.0.dist-info/entry_points.txt
h_yt_downloader-0.2.0.dist-info/METADATA
h_yt_downloader-0.2.0.dist-info/WHEEL
h_yt_downloader-0.2.0.dist-info/RECORD
