Metadata-Version: 2.1
Name: h_yt_downloader
Version: 0.2.0
Summary: 
Author: Henish Patel
Author-email: 200120107182@git.org.in
Requires-Python: >=3.12,<4.0
Classifier: Programming Language :: Python :: 3
Classifier: Programming Language :: Python :: 3.12
Requires-Dist: moviepy (>=1.0.3,<2.0.0)
Requires-Dist: pytube (>=15.0.0,<16.0.0)
